jtools/__init__.py
jtools/__test__.py
jtools/filter.py
jtools/formatter.py
jtools/query.py
jtools/grammar/JQLLexer.py
jtools/grammar/JQLListener.py
jtools/grammar/JQLParser.py
jtools/grammar/__init__.py
jtools/grammar/antlr_jql.py
jtools/grammar/jql.py
tests/__init__.py
tests/filter_tests.py
tests/formatter_tests.py
tests/manual_testing.py
tests/performance_tests.py
tests/query_tests.py
jtools-2.0.0.dist-info/LICENSE
jtools-2.0.0.dist-info/METADATA
jtools-2.0.0.dist-info/WHEEL
jtools-2.0.0.dist-info/top_level.txt
jtools-2.0.0.dist-info/RECORD
