Metadata-Version: 2.1
Name: jtools
Version: 2.0.0
Summary: A Python module that aids filtering, formatting, and transforming JSON-like objects
Home-page: https://github.com/BlendingJake/JTools-Py
Author: Jacob Morris
Author-email: blendingjake@gmail.com
License: UNKNOWN
Platform: UNKNOWN
Classifier: Programming Language :: Python :: 3
Classifier: License :: OSI Approved :: MIT License
Classifier: Operating System :: OS Independent
Classifier: Topic :: Database
Classifier: Topic :: Utilities
Requires-Python: >=3.5
Requires-Dist: python-dateutil (>=2)
Requires-Dist: antlr4-python3-runtime (>=4.8)
